commanger/NoneVar.py
commanger/__init__.py
commanger/exceptions.py
commanger/tools.py
commanger-0.1.3.dist-info/WHEEL
commanger-0.1.3.dist-info/METADATA
commanger-0.1.3.dist-info/RECORD
