Metadata-Version: 2.1
Name: commanger
Version: 0.1.3
Summary: A easy to use, extremely configurable shell/terminal command manager for python.
Author: ThatRandomPerson
Requires-Python: >=3.8,<4.0
Classifier: Programming Language :: Python :: 3
Classifier: Programming Language :: Python :: 3.10
Classifier: Programming Language :: Python :: 3.8
Classifier: Programming Language :: Python :: 3.9
Requires-Dist: colorama (>=0.4.5,<0.5.0)
Requires-Dist: pyparsing (>=3.0.9,<4.0.0)
